numt/__init__.py
numt/calc_tools.py
numt/common/__init__.py
numt/common/constants.py
numt/currency.py
numt/date_format.py
numt/digital.py
numt/education.py
numt/measurement_imperial.py
numt/measurement_si.py
numt/numeral.py
numt/phone.py
numt/scientific.py
numt/utils.py
numt-0.1.1.dist-info/LICENSE
numt-0.1.1.dist-info/METADATA
numt-0.1.1.dist-info/WHEEL
numt-0.1.1.dist-info/RECORD
