Metadata-Version: 2.3
Name: numt
Version: 0.1.1
Summary: A light-weight utility library for formatting numbers, currencies, dates, units, and more.
License: MIT
Keywords: formatting,numbers,units,humanize,utilities
Author: ajithvcoder
Author-email: ajithvcoder@gmail.com
Requires-Python: >=3.11,<4.0
Classifier: License :: OSI Approved :: MIT License
Classifier: Operating System :: OS Independent
Classifier: Programming Language :: Python :: 3
Classifier: Programming Language :: Python :: 3.11
Classifier: Programming Language :: Python :: 3.12
Classifier: Programming Language :: Python :: 3.13
Requires-Dist: Babel (>=2.9)
Project-URL: Documentation, https://github.com/YOUR_USERNAME/numt
Project-URL: Homepage, https://pypi.org/project/numt/
Project-URL: Repository, https://github.com/YOUR_USERNAME/numt
